fink_anomaly_detection_model/__init__.py
fink_anomaly_detection_model/data_transformer.py
fink_anomaly_detection_model/gui_model_validation.py
fink_anomaly_detection_model/main_script_.py
fink_anomaly_detection_model/reactions_reader.py
fink_anomaly_detection_model-0.4.81.dist-info/METADATA
fink_anomaly_detection_model-0.4.81.dist-info/WHEEL
fink_anomaly_detection_model-0.4.81.dist-info/entry_points.txt
fink_anomaly_detection_model-0.4.81.dist-info/top_level.txt
fink_anomaly_detection_model-0.4.81.dist-info/RECORD
