Metadata-Version: 2.4
Name: fink_anomaly_detection_model
Version: 0.4.81
Summary: Fink SNAD Anomaly Detection Model
Author-email: timofei.psheno@gmail.com
Requires-Python: >=3.9
Requires-Dist: scikit-learn>=1.3.1
Requires-Dist: numpy==1.26.4
Requires-Dist: pandas==2.0.2
Requires-Dist: tqdm>=4.65.0
Requires-Dist: scipy>=1.10.1
Requires-Dist: onnx==1.16.1
Requires-Dist: skl2onnx==1.17.0
Requires-Dist: pyarrow>=13.0.0
Requires-Dist: coniferest==0.1.1
Requires-Dist: telethon
Requires-Dist: slack_sdk
Requires-Dist: config
Requires-Dist: configparser
Requires-Dist: fink_science==3.13.3
Requires-Dist: Pillow
Requires-Dist: pyspark==3.1.3
Requires-Dist: light_curve
Requires-Dist: psutil
Requires-Dist: seaborn==0.13.2
Requires-Dist: matplotlib==3.9.0
Requires-Dist: optuna
Requires-Dist: requests
Dynamic: author-email
Dynamic: description
Dynamic: description-content-type
Dynamic: requires-dist
Dynamic: requires-python
Dynamic: summary
